<?xml version="1.0" encoding="utf-8"?>
<!--
Authors: Angles24 / Kayla / Lokibunny
Requires: ExBuddy Plugin & LLamaLibrary BotBase
-->
<Profile>
	<Name>Dragonsung Hatchet</Name>
	<Order>
	
	<RunCode Name="Disable_Flight"/>
	
	<If Condition="ClassName != ClassJobType.Botanist">
		<ChangeClass Job="Botanist"/>
	</If>
	<If Condition="ClassName == ClassJobType.Botanist and Core.Player.ClassLevel &gt; 79">
		
		<If Condition="not IsQuestCompleted(69384)">
			<If Condition="not HasQuest(69384) and not IsQuestCompleted(69384) and IsQuestCompleted(69208)">
				<GetTo ZoneId="418" XYZ="150.3899, -20, 64.72313"/>
				<If Condition="IsQuestAcceptQualified(69384)">
					<LLPickupQuest NpcId="1032897" DialogOption="0" QuestId="69384" XYZ="150.3899, -20, 64.72313"/>
					<LLSmallTalk/>
				</If>
			</If>
			<If Condition="HasQuest(69384) and not IsQuestCompleted(69384) and GetQuestStep(69384) == 255">
				<GetTo ZoneId="418" XYZ="-163.47, 16.97958, -29.31262"/>
				<LLTurnIn QuestId="69384" NpcId="1032898" XYZ="-163.47, 16.97958, -29.31262"/>
				<LLSmallTalk/>
				<WaitTimer WaitTime="2"/>
				<RunCode Name="Coffer"/>
			</If>
		</If>
		
		<If Condition="not IsQuestCompleted(69385) and IsQuestCompleted(69384)">
			<If Condition="not HasQuest(69385) and not IsQuestCompleted(69385) and IsQuestCompleted(69384)">
				<GetTo ZoneId="418" XYZ="-163.47, 16.97958, -29.31262"/>
				<If Condition="IsQuestAcceptQualified(69385)">
					<LLPickupQuest NpcId="1032898" QuestId="69385" XYZ="-163.47, 16.97958, -29.31262"/>
					<LLSmallTalk/>
				</If>
			</If>
		</If>
		
		<If Condition="not (HasItem(29620) or HasItem(29631) or HasItem(29642))">
			<GetTo ZoneId="418" XYZ="-161.5168, 16.99999, -57.14508"/>
			<BuyItem ItemId="29620" ItemCount="1" DialogOption="2" NpcId="1032900" XYZ="-161.5168, 16.99999, -57.14508"/>
		</If>
		
		<While Condition="HasItem(29620)"><!-- Skysteel Hatchet -->
			<If Condition="not HqHasAtLeast(29669,340) and not HasAtLeast(29670,120)">
				<Lisbeth Json="[{'Group':1,'Item':29670,'Amount':120,'Enabled':true,'Type':'Gather'},{'Id':1,'Group':1,'Item':29669,'Amount':340,'Enabled':true,'Type':'Gather','Hq':true}]"/>
			</If>
			<If Condition="HqHasAtLeast(29669,340) and not HasAtLeast(29670,120)">
				<Lisbeth Json="[{'Id':1,'Group':1,'Item':29670,'Amount':120,'Enabled':true,'Type':'Gather'}]"/>
			</If>
			<If Condition="not HqHasAtLeast(29669,340) and HasAtLeast(29670,120)">
				<Lisbeth Json="[{'Id':1,'Group':1,'Item':29669,'Amount':340,'Enabled':true,'Type':'Gather','Hq':true}]"/>
			</If>
			<!--<If Condition="not HqHasAtLeast(29669,340) or not HasAtLeast(29670,120)">
				<If Condition="ClassName != ClassJobType.Botanist">
					<ChangeClass Job="Botanist"/>
				</If>
				<While Condition="ff14bot.Managers.InventoryManager.GetBagByInventoryBagId(ff14bot.Enums.InventoryBagId.EquippedItems)[ff14bot.Enums.EquipmentSlot.MainHand].RawItemId != 29620">
					<RunCode Name="SkysteelBTN"/>
					<WaitTimer WaitTime="3"/>
				</While>
				<WaitTimer WaitTime="3"/>
				<AutoEquip/>
				<If Condition="not IsOnMap(398)">
					<GetTo ZoneId="398" XYZ="402.4343, -43.95806, -251.7982"/>
				</If>-->
				<!-- Fossil Dust -->
				<!--<ExGather while="not HasAtLeast(29670,120)" CordialType="Auto">
					<GatherObject>Mature Tree</GatherObject>
					<GatherSpots>
						<IndirectApproachGatherSpot ApproachLocation="382.2864, -46.41497, -149.7691" NodeLocation="379.8401, -46.12787, -149.9247" ReturnToApproachLocation="False"/>
					</GatherSpots>
					<HotSpots>
						<HotSpots Radius="30" X="381.0077" Y="-46.62662" Z="-147.4933"/>
						<HotSpots Radius="30" X="402.4373" Y="-43.95806" Z="-251.7982"/>
						<HotSpots Radius="30" X="301.5232" Y="-50.06977" Z="-288.1936"/>
					</HotSpots>
					<ItemNames>
						<ItemName>Oddly Specific Fossil Dust</ItemName>
						<ItemName>Oddly Specific Latex</ItemName>
					</ItemNames>
					<GatheringSkillOrder>
						<GatheringSkill SpellName="Blessed Harvest II" TimesToCast="1"/>
					</GatheringSkillOrder>
				</ExGather>-->
				<!-- Latex -->
				<!--<ExGather while="not HqHasAtLeast(29669,340)" CordialType="Auto">
					<GatherObject>Mature Tree</GatherObject>
					<GatherSpots>
						<IndirectApproachGatherSpot ApproachLocation="382.2864, -46.41497, -149.7691" NodeLocation="379.8401, -46.12787, -149.9247" ReturnToApproachLocation="False"/>
					</GatherSpots>
					<HotSpots>
						<HotSpots Radius="30" X="381.0077" Y="-46.62662" Z="-147.4933"/>
						<HotSpots Radius="30" X="402.4373" Y="-43.95806" Z="-251.7982"/>
						<HotSpots Radius="30" X="301.5232" Y="-50.06977" Z="-288.1936"/>
					</HotSpots>
					<ItemNames>
						<ItemName>Oddly Specific Latex</ItemName>
					</ItemNames>
					<GatheringSkillOrder>
						<GatheringSkill SpellName="Leaf Turn III" TimesToCast="1"/>
						<GatheringSkill SpellName="Blessed Harvest II" TimesToCast="1"/>
					</GatheringSkillOrder>
				</ExGather>
			</If>-->
			<While Condition="HasItem(29620) and HqHasAtLeast(29669,340) and HasAtLeast(29670,120)">
				<GetTo ZoneId="418" XYZ="-160.8965, 17.06712, -55.63131"/>
				<While Condition="ff14bot.Managers.InventoryManager.GetBagByInventoryBagId(ff14bot.Enums.InventoryBagId.EquippedItems)[ff14bot.Enums.EquipmentSlot.MainHand].RawItemId == 29620">
					<ChangeClass Job="Botanist"/>
					<WaitTimer WaitTime="3"/>
					<While Condition="ff14bot.Managers.InventoryManager.GetBagByInventoryBagId(ff14bot.Enums.InventoryBagId.EquippedItems)[ff14bot.Enums.EquipmentSlot.MainHand].RawItemId == 29620">
					<RunCode Name="SwitchCombatJob"/>
					</While>
				</While>
				<RunCode Name="Sort"/>
				<BuyShopExchangeItem NpcId="1032900" ItemId="29631" SelectString="0"/><!-- Buy Skysteel Hatchet +1 -->
				<WaitTimer WaitTime="3"/>
				<RunCode Name="CloseShop"/>
			</While>
		</While>
			
		<While Condition="HasItem(29631)"><!-- Skysteel Hatchet +1 -->
			<If Condition="not HasAtLeast(29675,180) and not HqHasAtLeast(29674,510)">
				<Lisbeth Json="[{'Group':1,'Item':29675,'Amount':180,'Enabled':true,'Type':'Gather'},{'Id':1,'Group':1,'Item':29674,'Amount':510,'Enabled':true,'Type':'Gather','Hq':true}]"/>
			</If>
			<If Condition="HasAtLeast(29675,180) and not HqHasAtLeast(29674,510)">
				<Lisbeth Json="[{'Id':1,'Group':1,'Item':29674,'Amount':510,'Enabled':true,'Type':'Gather','Hq':true}]"/>
			</If>
			<If Condition="not HasAtLeast(29675,180) and HqHasAtLeast(29674,510)">
				<Lisbeth Json="[{'Id':1,'Group':1,'Item':29675,'Amount':180,'Enabled':true,'Type':'Gather'}]"/>
			</If>
			<!--<If Condition="not HasAtLeast(29675,180)or not HqHasAtLeast(29674,510)">
				<If Condition="ClassName != ClassJobType.Botanist">
					<ChangeClass Job="Botanist"/>
				</If>
				<While Condition="ff14bot.Managers.InventoryManager.GetBagByInventoryBagId(ff14bot.Enums.InventoryBagId.EquippedItems)[ff14bot.Enums.EquipmentSlot.MainHand].RawItemId != 29631">
					<RunCode Name="SkysteelBTN2"/>
					<WaitTimer WaitTime="3"/>
				</While>
				<WaitTimer WaitTime="3"/>
				<AutoEquip/>
				<If Condition="not IsOnMap(397)">
					<GetTo ZoneId="397" XYZ="-617.2984, 118.947, -166.7891"/>
				</If>-->
				<!-- Striking Stone -->
				<!--<ExGather while="not HasAtLeast(29675,180)" CordialType="Auto">
					<GatherObject>Lush Vegetation Patch</GatherObject>
					<HotSpots>
						<HotSpot XYZ="-539.5354, 118.947, -189.7633" Radius="20"/>
						<HotSpot XYZ="-624.0922, 118.947, -252.8722" Radius="30"/>
						<HotSpot XYZ="-617.2984, 118.947, -166.7891" Radius="30"/>
					</HotSpots>
					<ItemNames>
						<ItemName>Oddly Specific Bauble</ItemName>
						<ItemName>Oddly Specific Amber</ItemName>
					</ItemNames>
					<GatheringSkillOrder>
						<GatheringSkill SpellName="Blessed Harvest II" TimesToCast="1"/>
					</GatheringSkillOrder>
				</ExGather>-->
				<!-- Amber -->
				<!--<ExGather while="not HqHasAtLeast(29674,510)" CordialType="Auto">
					<GatherObject>Lush Vegetation Patch</GatherObject>
					<HotSpots>
						<HotSpot XYZ="-539.5354, 118.947, -189.7633" Radius="20"/>
						<HotSpot XYZ="-624.0922, 118.947, -252.8722" Radius="30"/>
						<HotSpot XYZ="-617.2984, 118.947, -166.7891" Radius="30"/>
					</HotSpots>
					<ItemNames>
						<ItemName>Oddly Specific Amber</ItemName>
					</ItemNames>
					<GatheringSkillOrder>
						<GatheringSkill SpellName="Leaf Turn III" TimesToCast="1"/>
						<GatheringSkill SpellName="Blessed Harvest II" TimesToCast="1"/>
					</GatheringSkillOrder>
				</ExGather>
			</If>-->
			<While Condition="HasItem(29631) and HasAtLeast(29675,180) and HqHasAtLeast(29674,510)">
				<GetTo ZoneId="418" XYZ="-160.8965, 17.06712, -55.63131"/>
				<While Condition="ff14bot.Managers.InventoryManager.GetBagByInventoryBagId(ff14bot.Enums.InventoryBagId.EquippedItems)[ff14bot.Enums.EquipmentSlot.MainHand].RawItemId == 29631">
					<ChangeClass Job="Botanist"/>
					<WaitTimer WaitTime="3"/>
					<While Condition="ff14bot.Managers.InventoryManager.GetBagByInventoryBagId(ff14bot.Enums.InventoryBagId.EquippedItems)[ff14bot.Enums.EquipmentSlot.MainHand].RawItemId == 29631">
						<RunCode Name="SwitchCombatJob"/>
					</While>
				</While>
				<RunCode Name="Sort"/>
				<BuyShopExchangeItem NpcId="1032900" ItemId="29642" SelectString="1"/><!-- Buy Dragonsung Hatchet -->
				<WaitTimer WaitTime="3"/>
				<RunCode Name="CloseShop"/>
			</While>
		</While>
		
		<If Condition="HasItem(29642) and HasQuest(69385)">
			<While Condition="ClassName != ClassJobType.Botanist">
				<ChangeClass Job="Botanist"/>
			</While>
			<While Condition="ff14bot.Managers.InventoryManager.GetBagByInventoryBagId(ff14bot.Enums.InventoryBagId.EquippedItems)[ff14bot.Enums.EquipmentSlot.MainHand].RawItemId != 29642">
				<RunCode Name="SkysteelBTN3"/><!-- Equip Dragonsung Hatchet -->
				<WaitTimer WaitTime="3"/>
			</While>
			<If Condition="HasQuest(69385) and not IsQuestCompleted(69385) and GetQuestStep(69385) == 255">
				<GetTo ZoneId="418" XYZ="-165.3315, 16.97958, -30.53339"/>
				<LLTurnIn QuestId="69385" NpcId="1032899" XYZ="-165.3315, 16.97958, -30.53339"/>
				<LLSmallTalk/>
			</If>
		</If>
		
	</If>
	
	<LLoadProfile Path="../Skysteel Start.xml"/>
	
	</Order>
	<CodeChunks>
		<CodeChunk Name="Sort">
			<![CDATA[ 
				await Buddy.Coroutines.Coroutine.Sleep(1000);
				ff14bot.Managers.ChatManager.SendChat("/itemsort condition inventory hq des");
				await Buddy.Coroutines.Coroutine.Sleep(1000);
				ff14bot.Managers.ChatManager.SendChat("/itemsort execute inventory");
				await Buddy.Coroutines.Coroutine.Sleep(1000);
			]]>
		</CodeChunk>
		<CodeChunk Name="CloseShop">
			<![CDATA[ 
				var windowName = "ShopExchangeItem";
				await Coroutine.Wait(5000, () => RaptureAtkUnitManager.GetWindowByName(windowName) != null);				
				AtkAddonControl windowByName = RaptureAtkUnitManager.GetWindowByName(windowName);					
				windowByName = RaptureAtkUnitManager.GetWindowByName("ShopExchangeItem");
				await Coroutine.Wait(5000, () => windowByName != null);
				if (windowByName != null)
				windowByName.SendAction(1, 3uL, 4294967295uL);		
			]]>
		</CodeChunk>
		<CodeChunk Name="Coffer">
			<![CDATA[		
				foreach (var bagslot in InventoryManager.FilledSlots.Where(bagslot => bagslot.Item.ItemAction == 388))
				{
                bagslot.UseItem();
                await Coroutine.Sleep(5000);
				}
			]]> 
		</CodeChunk>
		<CodeChunk Name="SkysteelBTN">
			<![CDATA[ 
				BagSlot EquipSlot = ff14bot.Managers.InventoryManager.GetBagByInventoryBagId(ff14bot.Enums.InventoryBagId.EquippedItems)[ff14bot.Enums.EquipmentSlot.MainHand];
				foreach(ff14bot.Managers.BagSlot slot in ff14bot.Managers.InventoryManager.FilledInventoryAndArmory)
				{
					if(slot.RawItemId == 29620)
					{
						slot.Move(EquipSlot);
					}
				}
		]]>
		</CodeChunk>
		<CodeChunk Name="SkysteelBTN2">
			<![CDATA[ 
				BagSlot EquipSlot = ff14bot.Managers.InventoryManager.GetBagByInventoryBagId(ff14bot.Enums.InventoryBagId.EquippedItems)[ff14bot.Enums.EquipmentSlot.MainHand];
				foreach(ff14bot.Managers.BagSlot slot in ff14bot.Managers.InventoryManager.FilledInventoryAndArmory)
				{
					if(slot.RawItemId == 29631)
					{
						slot.Move(EquipSlot);
					}
				}
		]]>
		</CodeChunk>
		<CodeChunk Name="SkysteelBTN3">
			<![CDATA[ 
				BagSlot EquipSlot = ff14bot.Managers.InventoryManager.GetBagByInventoryBagId(ff14bot.Enums.InventoryBagId.EquippedItems)[ff14bot.Enums.EquipmentSlot.MainHand];
				foreach(ff14bot.Managers.BagSlot slot in ff14bot.Managers.InventoryManager.FilledInventoryAndArmory)
				{
					if(slot.RawItemId == 29642)
					{
						slot.Move(EquipSlot);
					}
				}
		]]>
		</CodeChunk>
		<CodeChunk Name="SwitchCombatJob">
            <![CDATA[ 
            var Combat = Enumerable.Range(8, 11).Append(0).Append(36);
            var gearSets = GearsetManager.GearSets.Where(i => i.InUse && !Combat.Contains((int)i.Class)).ToList().OrderByDescending(i=> i.Gear.First().Item.ItemLevel);

            if (gearSets.Any())
            {
                gearSets.First().Activate();
                await Coroutine.Sleep(2000);
            }
            ]]>
        </CodeChunk>
		<CodeChunk Name="Enable_Flight">
      <![CDATA[
        foreach (var plugin in PluginManager.Plugins.Where(p => p.Plugin.Name == "Enable Flight" || p.Plugin.Name == "启用飞行"))
        {
          try
          {
            if (plugin.Enabled)  {  break;  }  else  {  plugin.Enabled = true;  }
          }
          catch (Exception ex) {  }
        }
      ]]>
    </CodeChunk>
	<CodeChunk Name="Disable_Flight">
		<![CDATA[
			foreach (var plugin in PluginManager.Plugins.Where(p => p.Plugin.Name == "Enable Flight" || p.Plugin.Name == "启用飞行"))
			{
			try
			{
				if (!plugin.Enabled)  {  break;  }  else  {  plugin.Enabled = false;  }
			}
			catch (Exception ex) {  }
			}
		]]>
		</CodeChunk>
	</CodeChunks>
</Profile>